<?xml version="1.0" encoding="UTF-8"?>
<!--
    Licensed to the Apache Software Foundation (ASF) under one
    or more contributor license agreements.  See the NOTICE file
    distributed with this work for additional information
    regarding copyright ownership.  The ASF licenses this file
    to you under the Apache License, Version 2.0 (the
    "License"); you may not use this file except in compliance
    with the License.  You may obtain a copy of the License at

    http://www.apache.org/licenses/LICENSE-2.0

    Unless required by applicable law or agreed to in writing,
    software distributed under the License is distributed on an
    "AS IS" BASIS, WITHOUT WARRANTIES OR CONDITIONS OF ANY
    KIND, either express or implied.  See the License for the
    specific language governing permissions and limitations
    under the License.     
-->
<portlet-app xmlns="http://java.sun.com/xml/ns/portlet/portlet-app_2_0.xsd"
   xmlns:xsi="http://www.w3.org/2001/XMLSchema-instance"
   xsi:schemaLocation="http://java.sun.com/xml/ns/portlet/portlet-app_2_0.xsd http://java.sun.com/xml/ns/portlet/portlet-app_2_0.xsd"
   xmlns:tck="http://www.apache.org/portals/pluto/portlet-tck_3.0"
   version="2.0" id="V2SigTestsURL">
   <portlet>
      <portlet-name>SigTestsURL_BaseURL_SIGRenderActurl</portlet-name>
      <portlet-class>javax.portlet.tck.portlets.SigTestsURL_BaseURL_SIGRenderActurl</portlet-class>
      <expiration-cache>0</expiration-cache>
      <supports>
         <mime-type>text/html</mime-type>
      </supports>
      <supported-locale>en_US</supported-locale>
      <portlet-info>
         <title>SigTestsURL_BaseURL_SIGRenderActurl</title>
      </portlet-info>
   </portlet>

   <portlet>
      <portlet-name>SigTestsURL_BaseURL_SIGRenderRenurl</portlet-name>
      <portlet-class>javax.portlet.tck.portlets.SigTestsURL_BaseURL_SIGRenderRenurl</portlet-class>
      <expiration-cache>0</expiration-cache>
      <supports>
         <mime-type>text/html</mime-type>
      </supports>
      <supported-locale>en_US</supported-locale>
      <portlet-info>
         <title>SigTestsURL_BaseURL_SIGRenderRenurl</title>
      </portlet-info>
   </portlet>

   <portlet>
      <portlet-name>SigTestsURL_BaseURL_SIGRenderResurl</portlet-name>
      <portlet-class>javax.portlet.tck.portlets.SigTestsURL_BaseURL_SIGRenderResurl</portlet-class>
      <expiration-cache>0</expiration-cache>
      <supports>
         <mime-type>text/html</mime-type>
      </supports>
      <supported-locale>en_US</supported-locale>
      <portlet-info>
         <title>SigTestsURL_BaseURL_SIGRenderResurl</title>
      </portlet-info>
   </portlet>

   <portlet>
      <portlet-name>SigTestsURL_BaseURL_SIGResourceActurl</portlet-name>
      <portlet-class>javax.portlet.tck.portlets.SigTestsURL_BaseURL_SIGResourceActurl</portlet-class>
      <expiration-cache>0</expiration-cache>
      <supports>
         <mime-type>text/html</mime-type>
      </supports>
      <supported-locale>en_US</supported-locale>
      <portlet-info>
         <title>SigTestsURL_BaseURL_SIGResourceActurl</title>
      </portlet-info>
   </portlet>

   <portlet>
      <portlet-name>SigTestsURL_BaseURL_SIGResourceRenurl</portlet-name>
      <portlet-class>javax.portlet.tck.portlets.SigTestsURL_BaseURL_SIGResourceRenurl</portlet-class>
      <expiration-cache>0</expiration-cache>
      <supports>
         <mime-type>text/html</mime-type>
      </supports>
      <supported-locale>en_US</supported-locale>
      <portlet-info>
         <title>SigTestsURL_BaseURL_SIGResourceRenurl</title>
      </portlet-info>
   </portlet>

   <portlet>
      <portlet-name>SigTestsURL_BaseURL_SIGResourceResurl</portlet-name>
      <portlet-class>javax.portlet.tck.portlets.SigTestsURL_BaseURL_SIGResourceResurl</portlet-class>
      <expiration-cache>0</expiration-cache>
      <supports>
         <mime-type>text/html</mime-type>
      </supports>
      <supported-locale>en_US</supported-locale>
      <portlet-info>
         <title>SigTestsURL_BaseURL_SIGResourceResurl</title>
      </portlet-info>
   </portlet>

   <portlet>
      <portlet-name>SigTestsURL_PortletURL_SIGRenderActurl</portlet-name>
      <portlet-class>javax.portlet.tck.portlets.SigTestsURL_PortletURL_SIGRenderActurl</portlet-class>
      <expiration-cache>0</expiration-cache>
      <supports>
         <mime-type>text/html</mime-type>
      </supports>
      <supported-locale>en_US</supported-locale>
      <portlet-info>
         <title>SigTestsURL_PortletURL_SIGRenderActurl</title>
      </portlet-info>
   </portlet>

   <portlet>
      <portlet-name>SigTestsURL_PortletURL_SIGRenderRenurl</portlet-name>
      <portlet-class>javax.portlet.tck.portlets.SigTestsURL_PortletURL_SIGRenderRenurl</portlet-class>
      <expiration-cache>0</expiration-cache>
      <supports>
         <mime-type>text/html</mime-type>
      </supports>
      <supported-locale>en_US</supported-locale>
      <portlet-info>
         <title>SigTestsURL_PortletURL_SIGRenderRenurl</title>
      </portlet-info>
   </portlet>

   <portlet>
      <portlet-name>SigTestsURL_PortletURL_SIGResourceActurl</portlet-name>
      <portlet-class>javax.portlet.tck.portlets.SigTestsURL_PortletURL_SIGResourceActurl</portlet-class>
      <expiration-cache>0</expiration-cache>
      <supports>
         <mime-type>text/html</mime-type>
      </supports>
      <supported-locale>en_US</supported-locale>
      <portlet-info>
         <title>SigTestsURL_PortletURL_SIGResourceActurl</title>
      </portlet-info>
   </portlet>

   <portlet>
      <portlet-name>SigTestsURL_PortletURL_SIGResourceRenurl</portlet-name>
      <portlet-class>javax.portlet.tck.portlets.SigTestsURL_PortletURL_SIGResourceRenurl</portlet-class>
      <expiration-cache>0</expiration-cache>
      <supports>
         <mime-type>text/html</mime-type>
      </supports>
      <supported-locale>en_US</supported-locale>
      <portlet-info>
         <title>SigTestsURL_PortletURL_SIGResourceRenurl</title>
      </portlet-info>
   </portlet>

   <portlet>
      <portlet-name>SigTestsURL_ResourceURL_SIGRender</portlet-name>
      <portlet-class>javax.portlet.tck.portlets.SigTestsURL_ResourceURL_SIGRender</portlet-class>
      <expiration-cache>0</expiration-cache>
      <supports>
         <mime-type>text/html</mime-type>
      </supports>
      <supported-locale>en_US</supported-locale>
      <portlet-info>
         <title>SigTestsURL_ResourceURL_SIGRender</title>
      </portlet-info>
   </portlet>

   <event-definition>
      <qname>tck:SigTestsEvent_Event_SIGEvent</qname>
      <value-type>java.lang.String</value-type>
   </event-definition>

   <event-definition>
      <qname>tck:SigTestsEvent_EventRequest_SIGEvent</qname>
      <value-type>java.lang.String</value-type>
   </event-definition>

   <event-definition>
      <qname>tck:SigTestsEvent_EventResponse_SIGEvent</qname>
      <value-type>java.lang.String</value-type>
   </event-definition>

   <event-definition>
      <qname>tck:SigTestsEvent_PortletRequest_SIGEvent</qname>
      <value-type>java.lang.String</value-type>
   </event-definition>

   <event-definition>
      <qname>tck:SigTestsEvent_PortletResponse_SIGEvent</qname>
      <value-type>java.lang.String</value-type>
   </event-definition>

   <event-definition>
      <qname>tck:SigTestsEvent_StateAwareResponse_SIGEvent</qname>
      <value-type>java.lang.String</value-type>
   </event-definition>

   <public-render-parameter>
      <identifier>tckPRP1</identifier>
      <qname>tck:tckPRP1</qname>
   </public-render-parameter>
</portlet-app>
